alice_ml/__init__.py
alice_ml/features.py
alice_ml/metrics.py
alice_ml/models.py
alice_ml/preprocessing.py
alice_ml/upload.py
alice_ml/utils.py
alice_ml/vis.py
alice_ml/data/__init__.py
alice_ml/data/eye_blink_example.npy
alice_ml/data/eye_move_example.npy
alice_ml/data/pca_components.npy
alice_ml/data/pca_mean.npy
alice_ml/data/test_ica.fif
alice_ml/data/test_raw.fif
alice_ml/pretrained/__init__.py
alice_ml/pretrained/lr_flag_alpha.joblib
alice_ml/pretrained/lr_flag_brain.joblib
alice_ml/pretrained/lr_flag_ch_noise.joblib
alice_ml/pretrained/lr_flag_eyes.joblib
alice_ml/pretrained/lr_flag_heart.joblib
alice_ml/pretrained/lr_flag_mu.joblib
alice_ml/pretrained/lr_flag_muscles.joblib
alice_ml/pretrained/scaler.joblib
alice_ml/pretrained/svc_flag_brain.joblib
alice_ml/pretrained/svc_flag_eyes.joblib
alice_ml/pretrained/xgb_flag_brain.joblib
alice_ml/pretrained/xgb_flag_eyes.joblib
alice_ml/tests/__init__.py
alice_ml/tests/test_features.py
alice_ml/tests/test_models.py
alice_ml-0.3.9.dist-info/LICENSE
alice_ml-0.3.9.dist-info/METADATA
alice_ml-0.3.9.dist-info/WHEEL
alice_ml-0.3.9.dist-info/top_level.txt
alice_ml-0.3.9.dist-info/RECORD
