Metadata-Version: 2.1
Name: alice-ml
Version: 0.3.9
Summary: ALICE - Automated Labeling of Independent Components for EEG
Home-page: https://github.com/ALICE-EEG/alice-eeg-ml
Requires-Python: >=3.7
License-File: LICENSE
Requires-Dist: mne (>=0.23.4)
Requires-Dist: scikit-learn (>=1.0.1)
